src/AllEdgesDetection.py
src/__init__.py
EdgeDetector-1.0.0.dist-info/LICENSE
EdgeDetector-1.0.0.dist-info/METADATA
EdgeDetector-1.0.0.dist-info/WHEEL
EdgeDetector-1.0.0.dist-info/top_level.txt
EdgeDetector-1.0.0.dist-info/RECORD
